<item>
<title>[COLOR red]Contact @Shepo06 for requests or report any broken links[/COLOR]</title>
<link></link>
<thumbnail>http://i.imgur.com/CyTtpgR.png</thumbnail>
<fanart>http://i.imgur.com/vLyBcD1.jpg</fanart>
</item>

<item>
<title>[COLOR red]---------------------------------------------------------------[/COLOR]</title>
<link></link>
<thumbnail>http://i.imgur.com/CyTtpgR.png</thumbnail>
<fanart>http://i.imgur.com/vLyBcD1.jpg</fanart>
</item>

<item>
	<title>[COLOR white]A Fighting Man[/COLOR]</title>
	<meta>
		<content>movie</content>
		<imdb>tt2854894</imdb>
		<title>A Fighting Man</title>
		<year>2014</year>
	</meta>
	<link>
		<sublink>search</sublink>
		<sublink>searchsd</sublink>
	</link>
	<thumbnail>http://image.tmdb.org/t/p/original/eHlr18dramL3fSK7Kotg0fdTKl7.jpg</thumbnail>
	<fanart>http://image.tmdb.org/t/p/original/1qpmeLISO1qLIgKdkESuDIquq7I.jpg</fanart>
</item>

<item>
	<title>[COLOR white]Against the Ropes[/COLOR]</title>
	<meta>
		<content>movie</content>
		<imdb>tt0312329</imdb>
		<title>Against the Ropes</title>
		<year>2004</year>
	</meta>
	<link>
		<sublink>search</sublink>
		<sublink>searchsd</sublink>
	</link>
	<thumbnail>http://image.tmdb.org/t/p/original/hgNu3WqHS1Odvavs7X2GJyF9odt.jpg</thumbnail>
	<fanart>http://image.tmdb.org/t/p/original/yOUkVfaXDyklarpoJWbhnunqmGL.jpg</fanart>
</item>

<item>
	<title>[COLOR white]Any Which Way You Can[/COLOR]</title>
	<meta>
		<content>movie</content>
		<imdb>tt0080377</imdb>
		<title>Any Which Way You Can</title>
		<year>1980</year>
	</meta>
	<link>
		<sublink>search</sublink>
		<sublink>searchsd</sublink>
	</link>
	<thumbnail>http://image.tmdb.org/t/p/original/pd2wLrnIbPYSTeLERTsLpCAmRUn.jpg</thumbnail>
	<fanart>http://image.tmdb.org/t/p/original/pq5pTzVCj6jdnV9E6PXrBdXpKVb.jpg</fanart>
</item>

<item>
	<title>[COLOR white]Ali[/COLOR]</title>
	<meta>
		<content>movie</content>
		<imdb>tt0248667</imdb>
		<title>Ali</title>
		<year>2001</year>
	</meta>
	<link>
		<sublink>search</sublink>
		<sublink>searchsd</sublink>
	</link>
	<thumbnail>http://image.tmdb.org/t/p/w500/gCGoMZXGdU7DY8xgKYle6dJGksT.jpg</thumbnail>
	<fanart>http://image.tmdb.org/t/p/original/2IbajWDoPV6cjBjXhMpDvMsG4jZ.jpg</fanart>
</item>

<item>
	<title>[COLOR white]Bleed for This[/COLOR]</title>
	<meta>
		<content>movie</content>
		<imdb>tt1620935</imdb>
		<title>Bleed for This</title>
		<year>2016</year>
	</meta>
	<link>
		<sublink>search</sublink>
		<sublink>searchsd</sublink>
	</link>
	<thumbnail>http://image.tmdb.org/t/p/w500/lCjCMP4IYdSphkaQ19oqMKBKics.jpg</thumbnail>
	<fanart>http://image.tmdb.org/t/p/original/tJ9fIg4DDE3Zgjjio4ySlRxWcrn.jpg</fanart>
</item>

<item>
	<title>[COLOR white]Blood of a Champion[/COLOR]</title>
	<meta>
		<content>movie</content>
		<imdb>tt0427000</imdb>
		<title>Blood of a Champion</title>
		<year>2005</year>
	</meta>
	<link>
		<sublink>search</sublink>
		<sublink>searchsd</sublink>
	</link>
	<thumbnail>http://image.tmdb.org/t/p/original/yMGEtXFZ8X7P4kGIDK6QKGCUWNf.jpg</thumbnail>
	<fanart></fanart>
</item>

<item>
	<title>[COLOR white]Cardboard Boxer[/COLOR]</title>
	<meta>
		<content>movie</content>
		<imdb>tt3230660</imdb>
		<title>Cardboard Boxer</title>
		<year>2016</year>
	</meta>
	<link>
		<sublink>search</sublink>
		<sublink>searchsd</sublink>
	</link>
	<thumbnail>http://image.tmdb.org/t/p/original/rt2AKXnFiNhSLSnJ2yiAbMJKJFB.jpg</thumbnail>
	<fanart>http://image.tmdb.org/t/p/original/zhZOUl5iXSrYZjVAlQsQVw2QfKE.jpg</fanart>
</item>

<item>
	<title>[COLOR white]Chuck[/COLOR]</title>
	<meta>
		<content>movie</content>
		<imdb>tt1610525</imdb>
		<title>Chuck</title>
		<year>2016</year>
	</meta>
	<link>
		<sublink>search</sublink>
		<sublink>searchsd</sublink>
	</link>
	<thumbnail>https://images-na.ssl-images-amazon.com/images/M/MV5BYzkxYmFlNjQtMGY2Ni00ZDZmLTk4NzktMTc2Mzg0OTY5MjUyXkEyXkFqcGdeQXVyNTIyODMzMzA@._V1_SY1000_SX675_AL_.jpg</thumbnail>
	<fanart>https://i2.wp.com/teaser-trailer.com/wp-content/uploads/Chuck-movie-1.jpg?ssl=1</fanart>
</item>

<item>
	<title>[COLOR white]Cinderella Man[/COLOR]</title>
	<meta>
		<content>movie</content>
		<imdb>tt0352248</imdb>
		<title>Cinderella Man</title>
		<year>2005</year>
	</meta>
	<link>
		<sublink>search</sublink>
		<sublink>searchsd</sublink>
	</link>
	<thumbnail>http://image.tmdb.org/t/p/w500/xZhumK43Z6jmwCWglh7uHcpkqdb.jpg</thumbnail>
	<fanart>http://image.tmdb.org/t/p/original/ozvvHdadtBYpExCwAjsNPSjV6hT.jpg</fanart>
</item>

<item>
	<title>[COLOR white]Counterpunch[/COLOR]</title>
 	<meta>
  		<content>movie</content>
  		<imdb>tt7022034</imdb>
  		<title>Counterpunch</title>
  		<year>2017</year>
 	</meta>
 	<link>
		<sublink>https://openload.co/f/GBoIbwXk4wY/CounterPunch.2017.720p.NF.WEBRip.DD5.1.x264-FGT.mkv</sublink>
  		<sublink>search</sublink>
  		<sublink>searchsd</sublink>
 	</link>
 	<thumbnail>http://image.tmdb.org/t/p/w500/pkV3UPUqAZ9YsUDVQ6KfqpxeVP6.jpg</thumbnail>
 	<fanart>http://image.tmdb.org/t/p/original/wbDHjrSXTUWZ09OcF3gJGSmtFBE.jpg</fanart>
</item>

<item>
	<title>[COLOR white]Diggstown[/COLOR]</title>
	<meta>
		<content>movie</content>
		<imdb>tt0104107</imdb>
		<title>Diggstown</title>
		<year>1992</year>
	</meta>
	<link>
		<sublink>search</sublink>
		<sublink>searchsd</sublink>
	</link>
	<thumbnail>http://image.tmdb.org/t/p/original/e9yBRnykLUpjCsb7Wn1rRy2SphZ.jpg</thumbnail>
	<fanart>http://image.tmdb.org/t/p/original/ezBavKNifVsfhuJOdZgCaMDCJQ7.jpg</fanart>
</item>

<item>
	<title>[COLOR white]Every Which Way But Loose[/COLOR]</title>
	<meta>
		<content>movie</content>
		<imdb>tt0077523</imdb>
		<title>Every Which Way But Loose</title>
		<year>1978</year>
	</meta>
	<link>
		<sublink>search</sublink>
		<sublink>searchsd</sublink>
	</link>
	<thumbnail>http://image.tmdb.org/t/p/original/waGLjW4eC8zww90iTZKX7vFm2DM.jpg</thumbnail>
	<fanart>http://image.tmdb.org/t/p/original/4YdEQTF7wZyl2kTKsRc567Lp3q3.jpg</fanart>
</item>

<item>
	<title>[COLOR white]Far and Away[/COLOR]</title>
	<meta>
		<content>movie</content>
		<imdb>tt0104231</imdb>
		<title>Far and Away</title>
		<year>1992</year>
	</meta>
	<link>
		<sublink>search</sublink>
		<sublink>searchsd</sublink>
	</link>
	<thumbnail>http://image.tmdb.org/t/p/original/yNdfm55jkgFk1IeAqxSEPFDPR5x.jpg</thumbnail>
	<fanart>http://image.tmdb.org/t/p/original/lYTimGLaSjxZPiyoJjg3fHeCj5D.jpg</fanart>
</item>

<item>
	<title>[COLOR white]Fat City[/COLOR]</title>
	<meta>
		<content>movie</content>
		<imdb>tt0068575</imdb>
		<title>Fat City</title>
		<year>1972</year>
	</meta>
	<link>
		<sublink>search</sublink>
		<sublink>searchsd</sublink>
	</link>
	<thumbnail>http://image.tmdb.org/t/p/w500/xRjvUQqqMUACGre1IVJJwip8WVd.jpg</thumbnail>
	<fanart>http://image.tmdb.org/t/p/original/zGHWjvk0GL50OQQV76dJE31a3LU.jpg</fanart>
</item>

<item>
	<title>[COLOR white]Fighting[/COLOR]</title>
	<meta>
		<content>movie</content>
		<imdb>tt1082601</imdb>
		<title>Fighting</title>
		<year>2009</year>
	</meta>
	<link>
		<sublink>search</sublink>
		<sublink>searchsd</sublink>
	</link>
	<thumbnail>http://image.tmdb.org/t/p/original/yaZLB9FNV7Ivwu4mwDIsh320zDb.jpg</thumbnail>
	<fanart>http://image.tmdb.org/t/p/original/3UNBXbqijQFq45OqMJJgiSK4tDV.jpg</fanart>
</item>

<item>
	<title>[COLOR white]Girlfight[/COLOR]</title>
	<meta>
		<content>movie</content>
		<imdb>tt0210075</imdb>
		<title>Girlfight</title>
		<year>2000</year>
	</meta>
	<link>
		<sublink>search</sublink>
		<sublink>searchsd</sublink>
	</link>
	<thumbnail>http://image.tmdb.org/t/p/original/h9w0s4M7UAT6yMFv1Qw0Gp5qx9C.jpg</thumbnail>
	<fanart>http://image.tmdb.org/t/p/original/m9STTiP7PIxHrPkaDo8P3OKDdIw.jpg</fanart>
</item>

<item>
	<title>[COLOR white]Grudge Match[/COLOR]</title>
	<meta>
		<content>movie</content>
		<imdb>tt1661382</imdb>
		<title>Grudge Match</title>
		<year>2013</year>
	</meta>
	<link>
		<sublink>search</sublink>
		<sublink>searchsd</sublink>
	</link>
	<thumbnail>http://image.tmdb.org/t/p/w500/hScOPtZpAxYWx2sOGcfbzYti39Z.jpg</thumbnail>
	<fanart>http://image.tmdb.org/t/p/original/yJAicZoLQoVhY2rQGmUdcTP3pdw.jpg</fanart>
</item>

<item>
	<title>[COLOR white]Hands of Stone[/COLOR]</title>
	<meta>
		<content>movie</content>
		<imdb>tt1781827</imdb>
		<title>Hands of Stone</title>
		<year>2016</year>
	</meta>
	<link>
		<sublink>search</sublink>
		<sublink>searchsd</sublink>
	</link>
	<thumbnail>http://image.tmdb.org/t/p/w500/a6exWrG1tzVi87vktBdLzxVP7qQ.jpg</thumbnail>
	<fanart>http://image.tmdb.org/t/p/original/wweNPWBO4S2isIU7kgu1j4mmyMB.jpg</fanart>
</item>

<item>
	<title>[COLOR white]Hard Times[/COLOR]</title>
	<meta>
		<content>movie</content>
		<imdb>tt0073092</imdb>
		<title>Hard Times</title>
		<year>1975</year>
	</meta>
	<link>
		<sublink>search</sublink>
		<sublink>searchsd</sublink>
	</link>
	<thumbnail>http://image.tmdb.org/t/p/original/icKkYTBR5wowj9ZLpsMukVfG13H.jpg</thumbnail>
	<fanart>http://image.tmdb.org/t/p/original/cjvYMOIvPudHCgl2giPEugvbZDi.jpg</fanart>
</item>

<item>
	<title>[COLOR white]Homeboy[/COLOR]</title>
	<meta>
		<content>movie</content>
		<imdb>tt0095316</imdb>
		<title>Homeboy</title>
		<year>1988</year>
	</meta>
	<link>
		<sublink>search</sublink>
		<sublink>searchsd</sublink>
	</link>
	<thumbnail>http://image.tmdb.org/t/p/original/phAjRLZo6j7q1Q9iKvbgUlNnygh.jpg</thumbnail>
	<fanart>http://image.tmdb.org/t/p/original/5SpHvPoNpPrJHhXGvx9U3BlhIkt.jpg</fanart>
</item>

<item>
 <title>[COLOR white]Jawbone[/COLOR]</title>
 <meta>
  <content>movie</content>
  <imdb>tt3582020</imdb>
  <title>Jawbone</title>
  <year>2017</year>
 </meta>
 <link>
  <sublink>search</sublink>
  <sublink>searchsd</sublink>
 </link>
 <thumbnail>http://image.tmdb.org/t/p/w500/kvL3CZRILLJ9STxRadGXI0MOeac.jpg</thumbnail>
 <fanart>http://image.tmdb.org/t/p/original/wTdckA01HeJaSe36zC9xhBCbhBF.jpg</fanart>
</item>

<item>
	<title>[COLOR white]Knockout[/COLOR]</title>
	<meta>
		<content>movie</content>
		<imdb>tt1691453</imdb>
		<title>Knockout</title>
		<year>2011</year>
	</meta>
	<link>
		<sublink>search</sublink>
		<sublink>searchsd</sublink>
	</link>
	<thumbnail>http://image.tmdb.org/t/p/original/aXk7g93Fa1VlAVQMS07DIywE3xm.jpg</thumbnail>
	<fanart>http://image.tmdb.org/t/p/original/gaA8I4PuhU6hHMrcbRetqlYeoY5.jpg</fanart>
</item>

<item>
	<title>[COLOR white]Million Dollar Baby[/COLOR]</title>
	<meta>
		<content>movie</content>
		<imdb>tt0405159</imdb>
		<title>Million Dollar Baby</title>
		<year>2004</year>
	</meta>
	<link>
		<sublink>search</sublink>
		<sublink>searchsd</sublink>
	</link>
	<thumbnail>http://image.tmdb.org/t/p/w500/h4VZKi2Jt4VoBYJmtC4c3bO8KqM.jpg</thumbnail>
	<fanart>http://image.tmdb.org/t/p/original/o4OSztAvDYNDXkn9PJGbaQAO8VG.jpg</fanart>
</item>

<item>
 <title>[COLOR white]My Name Is Lenny[/COLOR]</title>
 <meta>
  <content>movie</content>
  <imdb>tt2024521</imdb>
  <title>My Name Is Lenny</title>
  <year>2017</year>
  <summary>The life story of one of Britain's most notorious bare-knuckle fighters, Lenny McLean, also known as "the Guv'nor."</summary>
 </meta>
 <link>
  <sublink>search</sublink>
  <sublink>searchsd</sublink>
 </link>
 <thumbnail>http://image.tmdb.org/t/p/w500/kvWLTH7YtyAYz1kfjzKR4qoY8Jq.jpg</thumbnail>
 <fanart>http://image.tmdb.org/t/p/original/u6G1tZquaUFAxKR3xXt9hEaJIIt.jpg</fanart>
</item>

<item>
 <title>[COLOR white]Notorious[/COLOR]</title>
 <meta>
  <content>movie</content>
  <imdb>tt7518466</imdb>
  <title>Notorious</title>
  <year>2017</year>
  <summary>Filmed over the course of 4 years, is a gripping access-all- areas account of McGregor's personal and professional journey from claiming benefits and living in his mum's spare room with his girlfriend to claiming multiple championship belts and 9-figure pay packets. Featuring exclusive interviews, unprecedented access and fight footage, this is the ultimate behind-the-scenes look at a sporting icon and his meteoric rise.</summary>
 </meta>
 <link>
  <sublink>search</sublink>
  <sublink>searchsd</sublink>
 </link>
 <thumbnail>https://images-na.ssl-images-amazon.com/images/M/MV5BNzI2M2YwOGMtNzIxNS00NzEyLWEzMzAtOGI1YzljNjRhMmU4XkEyXkFqcGdeQXVyNTM3MDMyMDQ@._V1_.jpg</thumbnail>
 <fanart>https://images-na.ssl-images-amazon.com/images/M/MV5BNzI2M2YwOGMtNzIxNS00NzEyLWEzMzAtOGI1YzljNjRhMmU4XkEyXkFqcGdeQXVyNTM3MDMyMDQ@._V1_.jpg</fanart>
</item>

<item>
	<title>[COLOR white]Phantom Punch[/COLOR]</title>
	<meta>
		<content>movie</content>
		<imdb>tt1131747</imdb>
		<title>Phantom Punch</title>
		<year>2009</year>
	</meta>
	<link>
		<sublink>search</sublink>
		<sublink>searchsd</sublink>
	</link>
	<thumbnail>http://image.tmdb.org/t/p/original/ferShvkqVS0oxzJg3QfjHIJSV8.jpg</thumbnail>
	<fanart>http://image.tmdb.org/t/p/original/yAOekttG7iiRHwYvSDC4AOXlhui.jpg</fanart>
</item>

<item>
	<title>[COLOR white]Play It to the Bone[/COLOR]</title>
	<meta>
		<content>movie</content>
		<imdb>tt0196857</imdb>
		<title>Play It to the Bone</title>
		<year>1999</year>
	</meta>
	<link>
		<sublink>search</sublink>
		<sublink>searchsd</sublink>
	</link>
	<thumbnail>http://image.tmdb.org/t/p/original/pVT6G8VZMd39iziJB4UZYwsRDAC.jpg</thumbnail>
	<fanart>http://image.tmdb.org/t/p/original/Ag5FK27xMQpmao27AzAV5kUfCOz.jpg</fanart>
</item>

<item>
	<title>[COLOR white]The Power of One[/COLOR]</title>
	<meta>
		<content>movie</content>
		<imdb>tt0105159</imdb>
		<title>The Power of One</title>
		<year>1992</year>
	</meta>
	<link>
		<sublink>search</sublink>
		<sublink>searchsd</sublink>
	</link>
	<thumbnail>http://image.tmdb.org/t/p/original/so9bcuzOJKMYQJETyOCLF5xH1LN.jpg</thumbnail>
	<fanart>http://image.tmdb.org/t/p/original/fdEuDn5tKH59CTV6Hw31Rht2AA9.jpg</fanart>
</item>

<item>
	<title>[COLOR white]Raging Bull[/COLOR]</title>
	<meta>
		<content>movie</content>
		<imdb>tt0081398</imdb>
		<title>Raging Bull</title>
		<year>1980</year>
	</meta>
	<link>
		<sublink>search</sublink>
		<sublink>searchsd</sublink>
	</link>
	<thumbnail>http://image.tmdb.org/t/p/w500/cbTfaMrWpZWwF3mY40v1SKaAVCx.jpg</thumbnail>
	<fanart>http://image.tmdb.org/t/p/original/yt88nEyDJLN8gOg1FTvCcXCM672.jpg</fanart>
</item>

<item>
	<title>[COLOR white]Real Steel[/COLOR]</title>
	<meta>
		<content>movie</content>
		<imdb>tt0433035</imdb>
		<title>Real Steel</title>
		<year>2011</year>
	</meta>
	<link>
		<sublink>search</sublink>
		<sublink>searchsd</sublink>
	</link>
	<thumbnail>http://image.tmdb.org/t/p/w500/drtXi58nN6P3zcoLh6wUlsZAYqh.jpg</thumbnail>
	<fanart>http://image.tmdb.org/t/p/original/pP2sONJEJraOioyrdCtwbVHDkRy.jpg</fanart>
</item>

<item>
	<title>[COLOR white]Resurrecting the Champ[/COLOR]</title>
	<meta>
		<content>movie</content>
		<imdb>tt0416185</imdb>
		<title>Resurrecting the Champ</title>
		<year>2007</year>
	</meta>
	<link>
		<sublink>search</sublink>
		<sublink>searchsd</sublink>
	</link>
	<thumbnail>http://image.tmdb.org/t/p/original/18epMloEUD83jCNQDHr8dRTaM8U.jpg</thumbnail>
	<fanart>http://image.tmdb.org/t/p/original/wBThIhD9OpTS29lhw7cqLvm9AcW.jpg</fanart>
</item>

<dir>
<item>
  <title>[COLOR white]Rocky Collection[/COLOR]</title>
  <meta>
    <content>movie</content>
    <imdb>tt0075148</imdb>
    <title>Rocky</title>
    <year>1976</year>
  </meta>
  <link>https://raw.githubusercontent.com/Shepo6/Shepo/master/addon_xmls/movies/rocky.xml</link>
  <thumbnail>http://is3.mzstatic.com/image/thumb/Video42/v4/fa/38/d8/fa38d8a3-6949-c994-66c9-b34820c1c869/source/1200x630bb.jpg</thumbnail>
  <fanart>http://image.tmdb.org/t/p/original/2kkyt0FLROrXt41IgSdE7goCFNQ.jpg</fanart>
</item>
</dir>

<item>
	<title>[COLOR white]Rocky Marciano[/COLOR]</title>
	<meta>
		<content>movie</content>
		<imdb>tt0183718</imdb>
		<title>Rocky Marciano</title>
		<year>1999</year>
	</meta>
	<link>
		<sublink>search</sublink>
		<sublink>searchsd</sublink>
	</link>
	<thumbnail>http://image.tmdb.org/t/p/original/uWmkapZbVv2pZDBxulx5wD6siBY.jpg</thumbnail>
	<fanart>http://image.tmdb.org/t/p/original/hUcZPmNndrgjZYngej7IUZCGnsx.jpg</fanart>
</item>

<item>
	<title>[COLOR white]Shiner[/COLOR]</title>
	<meta>
		<content>movie</content>
		<imdb>tt0232632</imdb>
		<title>Shiner</title>
		<year>2000</year>
	</meta>
	<link>
		<sublink>search</sublink>
		<sublink>searchsd</sublink>
	</link>
	<thumbnail>https://image.tmdb.org/t/p/original/fwVmRtvhzv4FXgdxUVVD3Hkb5lc.jpg</thumbnail>
	<fanart>http://image.tmdb.org/t/p/original/vFtvvdQiBI8KsPPTZAjusmJTETP.jpg</fanart>
</item>

<item>
	<title>[COLOR white]Snatch[/COLOR]</title>
	<meta>
		<content>movie</content>
		<imdb>tt0208092</imdb>
		<title>Snatch</title>
		<year>2000</year>
	</meta>
	<link>
		<sublink>search</sublink>
		<sublink>searchsd</sublink>
	</link>
	<thumbnail>http://image.tmdb.org/t/p/original/on9JlbGEccLsYkjeEph2Whm1DIp.jpg</thumbnail>
	<fanart>http://image.tmdb.org/t/p/original/cNLZ7YGRikb4IsLblrzu86ndZPw.jpg</fanart>
</item>

<item>
	<title>[COLOR white]Southpaw[/COLOR]</title>
	<meta>
		<content>movie</content>
		<imdb>tt1798684</imdb>
		<title>Southpaw</title>
		<year>2015</year>
	</meta>
	<link>
		<sublink>search</sublink>
		<sublink>searchsd</sublink>
	</link>
	<thumbnail>http://image.tmdb.org/t/p/w500/50d0XQQETSyg3bwBXhC7K33pKgc.jpg</thumbnail>
	<fanart>http://image.tmdb.org/t/p/original/2vFH3ntJbBC7QCwB0nRJGLx0oPU.jpg</fanart>
</item>

<item>
	<title>[COLOR white]Split Decisions[/COLOR]</title>
	<meta>
		<content>movie</content>
		<imdb>tt0096161</imdb>
		<title>Split Decisions</title>
		<year>1988</year>
	</meta>
	<link>
		<sublink>search</sublink>
		<sublink>searchsd</sublink>
	</link>
	<thumbnail>http://image.tmdb.org/t/p/original/fGyEmYobcsjlc3cjW7GUJwnmqQo.jpg</thumbnail>
	<fanart></fanart>
</item>

<item>
	<title>[COLOR white]Streets of Gold[/COLOR]</title>
	<meta>
		<content>movie</content>
		<imdb>tt0092022</imdb>
		<title>Streets of Gold</title>
		<year>1986</year>
	</meta>
	<link>
		<sublink>search</sublink>
		<sublink>searchsd</sublink>
	</link>
	<thumbnail>http://image.tmdb.org/t/p/original/jMHg3e0spSHEYtxtESldKfraOPT.jpg</thumbnail>
	<fanart>http://image.tmdb.org/t/p/original/dYHjjugpQ0VYLQFmVD7JCv3R0Nv.jpg</fanart>
</item>

<item>
	<title>[COLOR white]Strength and Honour[/COLOR]</title>
	<meta>
		<content>movie</content>
		<imdb>tt0787515</imdb>
		<title>Strength and Honour</title>
		<year>2007</year>
	</meta>
	<link>
		<sublink>search</sublink>
		<sublink>searchsd</sublink>
	</link>
	<thumbnail>http://image.tmdb.org/t/p/original/ssUF4lGHPdJffLMxm5h708D6hRO.jpg</thumbnail>
	<fanart>http://image.tmdb.org/t/p/original/cQ16qOlPiyRRz93q12ygnVxkeYS.jpg</fanart>
</item>

<item>
	<title>[COLOR white]The Big Man[/COLOR]</title>
	<meta>
		<content>movie</content>
		<imdb>tt0099136</imdb>
		<title>The Big Man</title>
		<year>1990</year>
	</meta>
	<link>
		<sublink>search</sublink>
		<sublink>searchsd</sublink>
	</link>
	<thumbnail>http://image.tmdb.org/t/p/original/vvlcNSBdFe2IEVXkDqhK6jr32B6.jpg</thumbnail>
	<fanart>http://image.tmdb.org/t/p/original/5X0l0G0S95iTzJMptyIMZO80XNS.jpg</fanart>
</item>

<item>
	<title>[COLOR white]The Boxer[/COLOR]</title>
	<meta>
		<content>movie</content>
		<imdb>tt0118760</imdb>
		<title>The Boxer</title>
		<year>1997</year>
	</meta>
	<link>
		<sublink>search</sublink>
		<sublink>searchsd</sublink>
	</link>
	<thumbnail>http://image.tmdb.org/t/p/w500/g8xzYsS6D2AE2luJIYmRZcxG0C2.jpg</thumbnail>
	<fanart>http://image.tmdb.org/t/p/original/hoSq8nfqK0CnsltyOTIA7JPVpeN.jpg</fanart>
</item>

<item>
	<title>[COLOR white]The Calcium Kid[/COLOR]</title>
	<meta>
		<content>movie</content>
		<imdb>tt0330111</imdb>
		<title>The Calcium Kid</title>
		<year>2004</year>
	</meta>
	<link>
		<sublink>search</sublink>
		<sublink>searchsd</sublink>
	</link>
	<thumbnail>http://image.tmdb.org/t/p/original/zwv9h53QJ5NKhxKcU8jMhktVad7.jpg</thumbnail>
	<fanart>http://image.tmdb.org/t/p/original/fHX5w6qFgCX6OWUhwDc3WHLNT7m.jpg</fanart>
</item>

<item>
	<title>[COLOR white]The Champ[/COLOR]</title>
	<meta>
		<content>movie</content>
		<imdb>tt0078950</imdb>
		<title>The Champ</title>
		<year>1979</year>
	</meta>
	<link>
		<sublink>search</sublink>
		<sublink>searchsd</sublink>
	</link>
	<thumbnail>http://image.tmdb.org/t/p/w500/oGKq9sTNCYLbKldtWobhz8nV445.jpg</thumbnail>
	<fanart>http://image.tmdb.org/t/p/original/9zfIXbAmCkxcw1OvytSHNATLCjP.jpg</fanart>
</item>

<item>
	<title>[COLOR white]The Fighter[/COLOR]</title>
	<meta>
		<content>movie</content>
		<imdb>tt0964517</imdb>
		<title>The Fighter</title>
		<year>2010</year>
	</meta>
	<link>
		<sublink>search</sublink>
		<sublink>searchsd</sublink>
	</link>
	<thumbnail>http://image.tmdb.org/t/p/w500/ytGIpdxYyvXwch5QILfquSTMA9f.jpg</thumbnail>
	<fanart>http://image.tmdb.org/t/p/original/vBIZjbQCFV52YcEHf99Mamrfele.jpg</fanart>
</item>

<item>
	<title>[COLOR white]The Great White Hope[/COLOR]</title>
	<meta>
		<content>movie</content>
		<imdb>tt0065797</imdb>
		<title>The Great White Hope</title>
		<year>1970</year>
	</meta>
	<link>
		<sublink>search</sublink>
		<sublink>searchsd</sublink>
	</link>
	<thumbnail>http://image.tmdb.org/t/p/w500/xijbD1c3ponKXX7TTOQZMg90U7j.jpg</thumbnail>
	<fanart>http://image.tmdb.org/t/p/original/mgQtJ7qUAuwpAPE4ZMO4bW6rDZv.jpg</fanart>
</item>

<item>
	<title>[COLOR white]The Great White Hype[/COLOR]</title>
	<meta>
		<content>movie</content>
		<imdb>tt0116448</imdb>
		<title>The Great White Hype</title>
		<year>1996</year>
	</meta>
	<link>
		<sublink>search</sublink>
		<sublink>searchsd</sublink>
	</link>
	<thumbnail>http://image.tmdb.org/t/p/original/15x1IKSbzO3qX4191Wf9UpuwK8D.jpg</thumbnail>
	<fanart>http://image.tmdb.org/t/p/original/1yMdfyQr0FovHo7EXQPgJ5MjWQf.jpg</fanart>
</item>

<item>
	<title>[COLOR white]The Hammer[/COLOR]</title>
	<meta>
		<content>movie</content>
		<imdb>tt0814130</imdb>
		<title>The Hammer</title>
		<year>2007</year>
	</meta>
	<link>
		<sublink>search</sublink>
		<sublink>searchsd</sublink>
	</link>
	<thumbnail>http://image.tmdb.org/t/p/original/sNoV54FINT4dyZ0Imja6BludefP.jpg</thumbnail>
	<fanart>http://image.tmdb.org/t/p/original/pLk4aVc1pQOjjnrVJ7JBK3CSWtY.jpg</fanart>
</item>

<item>
	<title>[COLOR white]The Hurricane[/COLOR]</title>
	<meta>
		<content>movie</content>
		<imdb>tt0174856</imdb>
		<title>The Hurricane</title>
		<year>1999</year>
	</meta>
	<link>
		<sublink>search</sublink>
		<sublink>searchsd</sublink>
	</link>
	<thumbnail>http://image.tmdb.org/t/p/w500/6SoTMHbcZ6XItPiEfIe1WzeET3c.jpg</thumbnail>
	<fanart>http://image.tmdb.org/t/p/original/i8AGAKxZL5aXnDcXVOZK5JkkDhn.jpg</fanart>
</item>

<item>
	<title>[COLOR white]Undefeated[/COLOR]</title>
	<meta>
		<content>movie</content>
		<imdb>tt0327951</imdb>
		<title>Undefeated</title>
		<year>2003</year>
	</meta>
	<link>
		<sublink>search</sublink>
		<sublink>searchsd</sublink>
	</link>
	<thumbnail>http://image.tmdb.org/t/p/original/alAcSfmJdPELzUxl3K5i3YTCkg5.jpg</thumbnail>
	<fanart>http://image.tmdb.org/t/p/original/ude3yOIOJtfsE42k3hLTAMwygwD.jpg</fanart>
</item>

<item>
	<title>[COLOR white]Undisputed[/COLOR]</title>
	<meta>
		<content>movie</content>
		<imdb>tt0281322</imdb>
		<title>Undisputed</title>
		<year>2002</year>
	</meta>
	<link>
		<sublink>search</sublink>
		<sublink>searchsd</sublink>
	</link>
	<thumbnail>http://image.tmdb.org/t/p/original/dhBQvKYMayM61M7kHOk35IfpE8K.jpg</thumbnail>
	<fanart>http://image.tmdb.org/t/p/original/cd6ZWNGMuF8BuFQFYOmzOWRTXHU.jpg</fanart>
</item>

<item>                
	<title></ title>                                                                            //This does not affect the scraper title. this is just for show
	<meta>                                                                                      //Start of information gathered for movie
		<content>movie</content>                                                                //Type of media
		<imdb>tt0479143</imdb>                                                                  //imdb Movie id
		<title>Rocky Balboa</title>                                                             //This is the Title that the scraper searches for
		<year>2006</year>                                                                       //Year of Movie
	</meta>                                                                                     //End of information gathered for movie
	<link>                                                                                      //Opens link tag
		<sublink>search</sublink>                                                               //Search HD links as Priority
		<sublink>searchsd</sublink>                                                             //Search SD links if no HD links are found
	</link>                                                                                     //Opens link tag
	<thumbnail>http://image.tmdb.org/t/p/w500/usZMPGxyRsyOpX5nuqHFxH3qlMh.jpg</thumbnail>       //Thumbnail of Movie
	<fanart>http://image.tmdb.org/t/p/original/gcFhaI5IrKxvMs4TtvlHbYE4b0.jpg</fanart>          //Fanart of Movie
</item>